{
  "indexes": [
    {
      "collectionGroup": "Logs",
      "queryScope": "COLLECTION",
      "fields": [
        {
          "fieldPath": "cleared",
          "order": "ASCENDING"
        },
        {
          "fieldPath": "groupId",
          "order": "ASCENDING"
        },
        {
          "fieldPath": "user",
          "order": "ASCENDING"
        },
        {
          "fieldPath": "date",
          "order": "DESCENDING"
        }
      ]
    },
    {
      "collectionGroup": "Logs",
      "queryScope": "COLLECTION",
      "fields": [
        {
          "fieldPath": "cleared",
          "order": "ASCENDING"
        },
        {
          "fieldPath": "groupId",
          "order": "ASCENDING"
        },
        {
          "fieldPath": "user.id",
          "order": "ASCENDING"
        },
        {
          "fieldPath": "date",
          "order": "DESCENDING"
        }
      ]
    },
    {
      "collectionGroup": "Logs",
      "queryScope": "COLLECTION",
      "fields": [
        {
          "fieldPath": "groupId",
          "order": "ASCENDING"
        },
        {
          "fieldPath": "cleared",
          "order": "ASCENDING"
        },
        {
          "fieldPath": "date",
          "order": "DESCENDING"
        }
      ]
    },
    {
      "collectionGroup": "Logs",
      "queryScope": "COLLECTION",
      "fields": [
        {
          "fieldPath": "groupId",
          "order": "ASCENDING"
        },
        {
          "fieldPath": "id",
          "order": "ASCENDING"
        },
        {
          "fieldPath": "cleared",
          "order": "ASCENDING"
        }
      ]
    }
  ],
  "fieldOverrides": []
}
